qrImageIndexer/__init__.py
qrImageIndexer/__main__.py
qrImageIndexer/generate_qr_wrapper.py
qrImageIndexer/photo_sorter.py
qrImageIndexer/qr_generator.py
qrImageIndexer/write_pdf_fpf2.py
qrImageIndexer-0.7.4.dist-info/LICENSE
qrImageIndexer-0.7.4.dist-info/METADATA
qrImageIndexer-0.7.4.dist-info/WHEEL
qrImageIndexer-0.7.4.dist-info/top_level.txt
qrImageIndexer-0.7.4.dist-info/RECORD
