Metadata-Version: 2.1
Name: qrImageIndexer
Version: 0.7.4
Summary: Tool for indexing images with QR codes
Author-email: Jonathan Pecar <jonathan.pecar@gmail.com>
License: MIT License
Project-URL: Homepage, https://github.com/jonpecar/qrCodeImageSorter
Keywords: sorter,qrcode,photosorter
Classifier: License :: OSI Approved :: MIT License
Classifier: Programming Language :: Python
Classifier: Programming Language :: Python :: 3
Requires-Python: >=3.6
License-File: LICENSE
Requires-Dist: pyzbar
Requires-Dist: pillow
Requires-Dist: fpdf2
Requires-Dist: qrcode
Requires-Dist: tqdm
Requires-Dist: opencv-python
Provides-Extra: dev
Requires-Dist: pytest ; extra == 'dev'
Requires-Dist: bumpver ; extra == 'dev'
Requires-Dist: setuptools ; extra == 'dev'
